dp/__init__.py
dp/addon.py
dp/components.py
dp/infos.py
dp/pager.py
dp/pyeval.py
dp/utils.py
dico_dp-0.0.6.dist-info/LICENSE
dico_dp-0.0.6.dist-info/METADATA
dico_dp-0.0.6.dist-info/WHEEL
dico_dp-0.0.6.dist-info/top_level.txt
dico_dp-0.0.6.dist-info/RECORD
