Metadata-Version: 2.1
Name: dico-dp
Version: 0.0.6
Summary: Simple debugger and tester for dico-command.
Home-page: https://github.com/dico-api/dico-dp
Author: eunwoo1104
Author-email: sions04@naver.com
License: UNKNOWN
Platform: UNKNOWN
Classifier: Programming Language :: Python :: 3
Requires-Python: >=3.7
License-File: LICENSE
Requires-Dist: dico-api
Requires-Dist: dico-command
Requires-Dist: psutil
